comicthumb/__init__.py
comicthumb/comicthumb.py
comicthumb-0.0.5.dist-info/LICENSE
comicthumb-0.0.5.dist-info/METADATA
comicthumb-0.0.5.dist-info/WHEEL
comicthumb-0.0.5.dist-info/entry_points.txt
comicthumb-0.0.5.dist-info/top_level.txt
comicthumb-0.0.5.dist-info/RECORD
