Metadata-Version: 2.1
Name: comicthumb
Version: 0.0.5
Summary: Python3 reimplementation of comix's comicthumb for generating comic thumbnails
License: GNU General Public License v2 (GPLv2)
Project-URL: repository, https://codeberg.org/johndovern/comicthumb
Keywords: comix,comicthumb,thumbnailer
License-File: LICENSE
Requires-Dist: pillow
